signalanalysislite/__init__.py
signalanalysislite/signalanalysislite.py
SignalAnalysisLite-0.0.1.dist-info/METADATA
SignalAnalysisLite-0.0.1.dist-info/WHEEL
SignalAnalysisLite-0.0.1.dist-info/top_level.txt
SignalAnalysisLite-0.0.1.dist-info/RECORD
