Metadata-Version: 2.1
Name: SignalAnalysisLite
Version: 0.0.1
Author-email: Russell Burgett <rwb273@cornell.edu>
Requires-Python: >=3.8
